.bumpversion.cfg
CONTRIBUTING.md
LICENSE
MANIFEST.in
Makefile
README.md
pyproject.toml
setup.py
docs/Makefile
docs/conf.py
docs/index.md
docs/make.bat
journalyze/__init__.py
journalyze/__main__.py
journalyze/_version.py
journalyze/journalyze.py
journalyze/prompts.csv
journalyze.egg-info/PKG-INFO
journalyze.egg-info/SOURCES.txt
journalyze.egg-info/dependency_links.txt
journalyze.egg-info/requires.txt
journalyze.egg-info/top_level.txt
journalyze/tests/test_all.py