Metadata-Version: 2.1
Name: journalyze
Version: 0.1.1
Summary: A journaling prompt library
Author-email: Johana De La Rosa <jed2192@columbia.edu>
License: MIT License
Project-URL: repository, https://github.com/jedlr/journalyze
Classifier: Development Status :: 2 - Pre-Alpha
Classifier: Programming Language :: Python :: Implementation :: CPython
Classifier: Programming Language :: Python :: Implementation :: PyPy
Classifier: Programming Language :: Python :: 3
Classifier: Programming Language :: Python :: 3.7
Classifier: Programming Language :: Python :: 3.8
Classifier: Programming Language :: Python :: 3.9
Classifier: Programming Language :: Python :: 3.10
Classifier: Programming Language :: Python :: 3.11
Requires-Python: >=3.7
Provides-Extra: develop
License-File: LICENSE
